pcldapy/__init__.py
pcldapy/pclda.py
pcldapy-0.0.3.dist-info/LICENCE
pcldapy-0.0.3.dist-info/METADATA
pcldapy-0.0.3.dist-info/WHEEL
pcldapy-0.0.3.dist-info/RECORD
